fluxfem/__init__.py
fluxfem/core/__init__.py
fluxfem/core/assembly.py
fluxfem/core/basis.py
fluxfem/core/context_types.py
fluxfem/core/data.py
fluxfem/core/dtypes.py
fluxfem/core/forms.py
fluxfem/core/interp.py
fluxfem/core/mixed_assembly.py
fluxfem/core/mixed_space.py
fluxfem/core/mixed_weakform.py
fluxfem/core/solver.py
fluxfem/core/space.py
fluxfem/core/weakform.py
fluxfem/helpers_ts.py
fluxfem/helpers_wf.py
fluxfem/mesh/__init__.py
fluxfem/mesh/base.py
fluxfem/mesh/contact.py
fluxfem/mesh/dtypes.py
fluxfem/mesh/hex.py
fluxfem/mesh/io.py
fluxfem/mesh/mortar.py
fluxfem/mesh/predicate.py
fluxfem/mesh/supermesh.py
fluxfem/mesh/surface.py
fluxfem/mesh/tet.py
fluxfem/physics/__init__.py
fluxfem/physics/diffusion.py
fluxfem/physics/elasticity/__init__.py
fluxfem/physics/elasticity/hyperelastic.py
fluxfem/physics/elasticity/linear.py
fluxfem/physics/elasticity/materials.py
fluxfem/physics/elasticity/stress.py
fluxfem/physics/operators.py
fluxfem/physics/postprocess.py
fluxfem/solver/__init__.py
fluxfem/solver/bc.py
fluxfem/solver/block_matrix.py
fluxfem/solver/block_system.py
fluxfem/solver/cg.py
fluxfem/solver/dirichlet.py
fluxfem/solver/history.py
fluxfem/solver/newton.py
fluxfem/solver/petsc.py
fluxfem/solver/preconditioner.py
fluxfem/solver/result.py
fluxfem/solver/solve_runner.py
fluxfem/solver/solver.py
fluxfem/solver/sparse.py
fluxfem/tools/__init__.py
fluxfem/tools/jit.py
fluxfem/tools/timer.py
fluxfem/tools/visualizer.py
fluxfem-0.2.1.dist-info/LICENSE
fluxfem-0.2.1.dist-info/METADATA
fluxfem-0.2.1.dist-info/WHEEL
fluxfem-0.2.1.dist-info/RECORD
