Metadata-Version: 2.1
Name: fluxfem
Version: 0.2.1
Summary: FluxFEM: A weak-form-centric differentiable finite element framework in JAX
License: Apache-2.0
Author: Kohei Watanabe
Author-email: koheitech001@gmail.com
Requires-Python: >=3.12,<3.14
Classifier: License :: OSI Approved :: Apache Software License
Classifier: Programming Language :: Python :: 3
Classifier: Programming Language :: Python :: 3.12
Provides-Extra: cpu
Provides-Extra: cuda12
Provides-Extra: petsc
Requires-Dist: jax (>=0.8.2,<0.9.0) ; extra == "cpu" or extra == "cuda12"
Requires-Dist: jax-cuda12-pjrt (==0.8.2) ; extra == "cuda12"
Requires-Dist: jax-cuda12-plugin (==0.8.2) ; extra == "cuda12"
Requires-Dist: jaxlib (>=0.8.2,<0.9.0) ; extra == "cpu" or extra == "cuda12"
Requires-Dist: matplotlib (>=3.10.7,<4.0.0)
Requires-Dist: meshio (>=5.3.5,<6.0.0)
Requires-Dist: petsc4py (==3.23.6) ; extra == "petsc"
Requires-Dist: pyproject (>=1!0.1.2,<1!0.2.0)
Requires-Dist: pyproject-toml (>=0.1.0,<0.2.0)
Requires-Dist: pyvista (>=0.46.4,<0.47.0)
